{
    "translation": {
    "Welcome": "స్వాగతం",
    "Contact_Us_sent": "మమ్మల్ని సంప్రదించడానికి, దయచేసి ఈ డొమైన్ [వద్ద] సమాచారం వద్ద ఇమెయిల్ పంపండి.",
    "Account": "ఖాతా",
    "Contact_Us": "మమ్మల్ని సంప్రదించండి",
    "FeedBack Form": "అభిప్రాయం",
    "FeedBackSent": "మీ అభిప్రాయాన్ని నమోదు చేయండి",
    "Suggestions": "సూచనలు",
    "SuggestionsSent": "మీ సూచనలను నమోదు చేయండి",
    "ReportIssue": "నివేదిక ఇష్యూ",
    "PlantInfo": "ప్లాంట్ ఇన్ఫో",
  "Contact": "సంప్రదించండి",
  "Feedback": "అభిప్రాయం",
  "Search": "వెతకండి",
  "MediScan": "మెడిస్కాన్",
  "Home": "హోమ్",
  "MedicinalPlantDetector": "మెడిసినల్ ప్లాంట్ డిటెక్టర్",
  "ClickOn": "కెమెరా / గ్యాలరీ నుండి చిత్రాన్ని అప్‌లోడ్ చేయడానికి క్రింది బటన్‌పై క్లిక్ చేయండి",
  "UploadImage": "చిత్రాన్ని అప్‌లోడ్ చేయండి",
  "UsageGuide": "వినియోగ గైడ్",
  "UsageGuide_1": "మొక్క లేదా ఆకు చిత్రాలను స్పష్టంగా మరియు బాగా దృష్టి కేంద్రీకరించే విధంగా క్యాప్చర్ చేయండి, ఇది మెరుగైన గుర్తింపులో సహాయపడుతుంది.",
  "UsageGuide_2": "మొక్కలో బహుళ కోణాలను చేర్చడానికి ప్రయత్నించండి మరియు చక్కటి వివరాలను సంగ్రహించడానికి అధిక రిజల్యూషన్ కెమెరాలను ఉపయోగించడం మంచిది.",
  "UsageGuide_3": "మీకు వాటి గురించి తెలియకపోతే ఏదైనా మోడల్‌ని ఎంచుకోండి మరియు మెరుగైన ఖచ్చితత్వాల కోసం మోడల్‌ను మార్చండి.",
  "UsageGuide_4": "మా శోధన ఫీచర్ ద్వారా భారతీయ ఔషధ జాతుల గురించి సమాచారం కోసం చూడండి.",
  "UsageGuide_5": "మీ చరిత్ర మా అప్లికేషన్‌లో సేవ్ చేయబడుతుంది మరియు మీరు వాటిని తర్వాత ఉపయోగించవచ్చు.",
  "UsageGuide_6": "దయచేసి అంచనా యొక్క ఖచ్చితత్వాలపై మీ అభిప్రాయాన్ని పంచుకోండి మరియు ఇది మా నమూనాను మెరుగుపరచడంలో మాకు సహాయపడుతుంది.",
  "Accuarate": "మీ AI అంచనా ఎంత ఖచ్చితమైనది?",
  "AccurateSentence": "ఏ ఆర్టిఫిషియల్ ఇంటెలిజెన్స్ మోడల్ సరైనది కాదు మరియు అలాంటి మోడల్ ఎప్పటికీ ఉండదని మాకు తెలుసు. ",
  "PlantIdentificationSentence": "పుష్ప వైవిధ్యం యొక్క గొప్ప వారసత్వం కలిగిన భారతదేశం, ఔషధ మొక్కల సంపదకు ప్రసిద్ధి చెందింది, అయితే ఆయుర్వేద ఫార్మాస్యూటిక్స్‌లో వాటి గుర్తింపు ప్రధాన బర్నింగ్ సమస్యలలో ఒకటి. ",
  "PlantIdentification": "మొక్కల గుర్తింపు సులభం",
  "AiHardWork": "AI కష్టపడి పని చేయనివ్వండి",
  "AiHardWorkSentence": "ప్రతి ఔషధ మొక్క ప్రత్యేకమైన చికిత్సా లక్షణాలను అందిస్తుంది. ",
  "ReportIssueSent": "ఏదైనా సమస్య ఉంటే, దయచేసి నివేదించండి లేదా ఖాళీగా ఉంచండి",
  "Gallery": "గ్యాలరీ",
  "About": "గురించి",
  "Search for a herb here":"ఇక్కడ మూలికల కోసం వెతకండి"
  }
}